<!-- xml reconstructed by Source 2 Viewer 10.2.0.0 - https://valveresourceformat.github.io -->
<root>
	<styles>
		<include src="s2r://panorama/styles/gamestyles.vcss_c" />
		<include src="s2r://panorama/styles/popups/popups_shared.vcss_c" />
		<include src="s2r://panorama/styles/mainmenu.vcss_c" />
		<include src="s2r://panorama/styles/popups/popup_inventory_inspect.vcss_c" />
		<include src="s2r://panorama/styles/popups/popup_capability_shared.vcss_c" />
	</styles>
	<scripts>
		<include src="s2r://panorama/scripts/common/iteminfo.vts_c" />
		<include src="s2r://panorama/scripts/popups/popup_inspect_rental-bar.vts_c" />
	</scripts>
	<Panel class="popup-capability__button-row" useglobalcontext="true">
		<Panel class="popup-capability__purchase">
			<TextButton id="" class="PopupButton" text="#Store_Close" onactivate="InspectPurchaseBar.ClosePopup();" />
			<Panel id="id-rental-section" class="right-left-flow">
				<Panel class="popup-capability__seperator" />
				<Button id="RentBtn" class="rent-bar-btn">
					<Panel id="id-spinner" class="Spinner" />
					<Panel class="rent-bar-btn-text">
						<Label class="rent-bar-btn-title stratum-medium-condensed" text="#popup_decodable_rent_weapons" />
						<Label class="rent-bar-btn-subtitle stratum-regular" text="#popup_decodable_rent_weapon_count" />
					</Panel>
				</Button>
				<Button id="OpenBtn" class="rent-bar-btn">
					<Panel id="id-spinner" class="Spinner" />
					<Panel class="rent-bar-btn-text">
						<Label class="rent-bar-btn-title stratum-medium-condensed" text="#popup_decodable_open_case" />
						<Label class="rent-bar-btn-subtitle stratum-regular" text="#popup_decodable_keep_weapon" />
					</Panel>
				</Button>
				<Label id="UseItemName" html="true" class="popup-capability__purchase__text stratum-font" text="" />
				<ItemImage id="UseItemImage" class="popup-capability__purchase__image" scaling="stretch-to-fit-x-preserve-aspect" />
			</Panel>
			<Panel id="id-rental-xray-section" class="right-left-flow">
				<Panel class="popup-capability__seperator" />
				<Button id="PurchaseKeyBtn" class="rent-bar-btn hide">
					<Panel id="id-spinner" class="Spinner" />
					<ItemImage id="SellItemImage" class="popup-capability__purchase__image" scaling="stretch-to-fit-x-preserve-aspect" />
					<Panel class="rent-bar-btn-text">
						<Label class="rent-bar-btn-title stratum-medium-condensed" text="#popup_decodable_rent_weapons" />
						<Label class="rent-bar-btn-subtitle stratum-regular" html="true" text="#popup_decodable_rent_get_key" />
					</Panel>
				</Button>
				<Button id="RentBtnXray" class="rent-bar-btn hide">
					<Panel id="id-spinner" class="Spinner" />
					<Panel class="rent-bar-btn-text">
						<Label class="rent-bar-btn-title stratum-medium-condensed" text="#popup_decodable_rent_weapons" />
						<Label class="rent-bar-btn-subtitle stratum-regular" text="#popup_decodable_rent_weapon_count" />
					</Panel>
				</Button>
				<Button id="OpenXray" class="rent-bar-btn">
					<Panel id="id-spinner" class="Spinner" />
					<Panel class="rent-bar-btn-text">
						<Label class="rent-bar-btn-title stratum-medium-condensed" text="#inv_context_xray" />
						<Label class="rent-bar-btn-subtitle stratum-regular" text="#popup_xray_reveal_warning_short" />
					</Panel>
				</Button>
			</Panel>
		</Panel>
	</Panel>
</root>
