<!-- xml reconstructed by Source 2 Viewer 7.0.0.0 - https://valveresourceformat.github.io -->
<root>
	<styles>
		<include src="s2r://panorama/styles/csgostyles.vcss_c" />
		<include src="s2r://panorama/styles/popups/popups_shared.vcss_c" />
		<include src="s2r://panorama/styles/mainmenu.vcss_c" />
		<include src="s2r://panorama/styles/popups/popup_capability_can_stattrack_swap.vcss_c" />
		<include src="s2r://panorama/styles/popups/popup_capability_shared.vcss_c" />
	</styles>
	<scripts>
		<include src="s2r://panorama/scripts/inspect.vts_c" />
		<include src="s2r://panorama/scripts/popups/popup_capability_can_stattrack_swap.vjs_c" />
		<include src="s2r://panorama/scripts/common/iteminfo.vts_c" />
	</scripts>
	<PopupCustomLayout class="PopupPanel Capability Hidden" useglobalcontext="true" popupbackground="blur" oncancel="CapabilityCanStatTrackSwap.ClosePopup();" onload="CapabilityCanStatTrackSwap.Init();">
		<Panel id="NameableSpinner" class="Spinner vertical-center horizontal-center hidden" />
		<Panel class="mainmenu-content__container mainmenu-content__container--inspect" hittest="true">
			<Panel class="full-width full-height">
				<Panel class="popup-stattrackswap-item-models">
					<Panel class="popup-stattrackswap-two-models">
						<Frame id="StatTrackSwapItemModel0" class="StatTrackSwapItemModel" src="s2r://panorama/layout/inspect.vxml_c" />
						<Panel class="StatTrackSwapNumberVerticalSpacer" />
						<Frame id="StatTrackSwapItemModel1" class="StatTrackSwapItemModel" src="s2r://panorama/layout/inspect.vxml_c" />
					</Panel>
					<Panel class="popup-stattrackswap-two-models">
						<Panel class="StatTrackSwapNumberPadding" />
						<Label id="StatTrackSwapNumber0" class="StatTrackSwapNumber MonoNumbersFont" text="" html="true" />
						<Label id="StatTrackSwapNumber1" class="StatTrackSwapNumber MonoNumbersFont" text="" html="true" />
						<Panel class="StatTrackSwapNumberPadding" />
					</Panel>
				</Panel>
				<Panel class="popup-capability__top">
					<Label id="StatTrackSwapTitle" class="popup-capability__name horizontal-center" text="#ToolType_stattrak_swap" />
					<Label id="StatTrackSwapDesc" html="true" class="fontSize-l horizontal-center" text="#CSGO_tool_stattrak_swap_desc" />
					<Panel class="left-right-flow horizontal-center top-padding">
						<Image class="right-padding" texturewidth="24" textureheight="-1" src="s2r://panorama/images/icons/ui/info.vsvg" />
						<Label html="true" class="fontSize-m vertical-center text-align-center" text="#SFUI_Statrak_Swap_Warning" />
					</Panel>
				</Panel>
				<Panel class="popup-capability__button-row">
					<Panel class="left-right-flow horizontal-align-right">
						<TextButton id="StatTrackSwapAcceptConfirm" class="PopupButton Positive" text="#SFUI_Accept" />
						<TextButton id="StatTrackSwapCancelBtn" class="PopupButton" text="#GameUI_Close" />
					</Panel>
				</Panel>
			</Panel>
		</Panel>
	</PopupCustomLayout>
</root>
