<!-- xml reconstructed by Source 2 Viewer 7.0.0.0 - https://valveresourceformat.github.io -->
<root>
	<styles>
		<include src="s2r://panorama/styles/csgostyles.vcss_c" />
		<include src="s2r://panorama/styles/hud/hudautodisconnect.vcss_c" />
	</styles>
	<CSGOHudAutoDisconnect class="auto-disconnect">
		<Panel class="auto-disconnect-container">
			<Panel id="TopContainer">
				<Label id="TopLabel" class="auto-disconnect_top-label stratum-medium" />
			</Panel>
			<Panel id="BottomContainer" class="bottom-container">
				<Label id="BottomLabel" class="auto-disconnect_bottom-label" />
				<Image id="TimerIcon" texturewidth="-1" textureheight="28" src="s2r://panorama/images/icons/ui/clock.vsvg" />
			</Panel>
		</Panel>
	</CSGOHudAutoDisconnect>
</root>
